hackerakos/__init__.py
hackerakos/src/__init__.py
hackerakos/src/hackerakos.py
hackerakos/src/utils.py
simtkinter-0.0.3.dist-info/LICENSE
simtkinter-0.0.3.dist-info/METADATA
simtkinter-0.0.3.dist-info/WHEEL
simtkinter-0.0.3.dist-info/top_level.txt
simtkinter-0.0.3.dist-info/RECORD
