Metadata-Version: 2.1
Name: simtkinter
Version: 0.0.3
Summary: Makes the Tkinter simpler
Home-page: http://hacker-bin.com
Author: Hackerakos
Author-email: hackerakos@hacker-bin.com
License: MIT
Classifier: License :: OSI Approved :: MIT License
Classifier: Programming Language :: Python :: 3.12
Classifier: Operating System :: OS Independent
Requires-Python: >=3.10
License-File: LICENSE
